quickkey/__init__.py
quickkey/assets/quick_key.ico
quickkey/quick_key.py
quickkey-0.1.4.dist-info/entry_points.txt
quickkey-0.1.4.dist-info/LICENSE
quickkey-0.1.4.dist-info/METADATA
quickkey-0.1.4.dist-info/WHEEL
quickkey-0.1.4.dist-info/RECORD
